{
  "key": "https://data.cityofnewyork.us/resource/ipu4-2q9a.json?bin__=5107019&%24order=issuance_date+DESC&%24limit=50000&%24offset=0",
  "recordedAt": "2026-07-06T04:52:07.427Z",
  "value": [
    {
      "borough": "STATEN ISLAND",
      "bin__": "5107019",
      "house__": "2111",
      "street_name": "RICHMOND TERRACE",
      "job__": "520333559",
      "job_doc___": "01",
      "job_type": "NB",
      "self_cert": "Y",
      "block": "01068",
      "lot": "00072",
      "community_board": "501",
      "zip_code": "10302",
      "bldg_type": "2",
      "permit_status": "ISSUED",
      "filing_status": "RENEWAL",
      "permit_type": "NB",
      "permit_sequence__": "04",
      "site_fill": "USE UNDER 300 CU.YD",
      "filing_date": "12/31/2021",
      "issuance_date": "12/31/2021",
      "expiration_date": "04/01/2022",
      "job_start_date": "06/25/2020",
      "permittee_s_first_name": "PHILIP",
      "permittee_s_last_name": "APAP",
      "permittee_s_business_name": "HUDSON RIVER CONTRACTING*",
      "permittee_s_phone__": "8455621350",
      "permittee_s_license_type": "GC",
      "permittee_s_license__": "0610584",
      "superintendent_first___last_name": "PAUL APAP",
      "superintendent_business_name": "HUDSON RIVER CONTRACTING",
      "owner_s_business_type": "CORPORATION",
      "non_profit": "N",
      "owner_s_business_name": "AMERCO REAL ESTATE COMPANY",
      "owner_s_first_name": "CARLOS",
      "owner_s_last_name": "VIZCARRA",
      "permit_si_no": "3887998",
      "gis_latitude": "40.640322",
      "gis_longitude": "-74.133391",
      "gis_council_district": "49",
      "gis_census_tract": "20702",
      "bbl": "5010680072",
      "gis_nta_name": "Port Richmond",
      "dobrundate": "2026-07-05T00:00:00.000"
    },
    {
      "borough": "STATEN ISLAND",
      "bin__": "5107019",
      "house__": "2111",
      "street_name": "RICHMOND TERRACE",
      "job__": "520333559",
      "job_doc___": "01",
      "job_type": "NB",
      "self_cert": "Y",
      "block": "01068",
      "lot": "00072",
      "community_board": "501",
      "zip_code": "10302",
      "bldg_type": "2",
      "permit_status": "ISSUED",
      "filing_status": "RENEWAL",
      "permit_type": "NB",
      "permit_sequence__": "08",
      "site_fill": "USE UNDER 300 CU.YD",
      "filing_date": "12/21/2023",
      "issuance_date": "12/21/2023",
      "expiration_date": "04/01/2024",
      "job_start_date": "06/25/2020",
      "permittee_s_first_name": "PHILIP",
      "permittee_s_last_name": "APAP",
      "permittee_s_business_name": "HUDSON RIVER CONTRACTING*",
      "permittee_s_phone__": "8455621350",
      "permittee_s_license_type": "GC",
      "permittee_s_license__": "0610584",
      "superintendent_first___last_name": "PAUL APAP",
      "superintendent_business_name": "HUDSON RIVER CONTRACTING",
      "owner_s_business_type": "CORPORATION",
      "non_profit": "N",
      "owner_s_business_name": "AMERCO REAL ESTATE COMPANY",
      "owner_s_first_name": "CARLOS",
      "owner_s_last_name": "VIZCARRA",
      "permit_si_no": "3969019",
      "gis_latitude": "40.640322",
      "gis_longitude": "-74.133391",
      "gis_council_district": "49",
      "gis_census_tract": "20702",
      "bbl": "5010680072",
      "gis_nta_name": "Port Richmond",
      "dobrundate": "2026-07-05T00:00:00.000"
    },
    {
      "borough": "STATEN ISLAND",
      "bin__": "5107019",
      "house__": "2111",
      "street_name": "RICHMOND TERRACE",
      "job__": "520333559",
      "job_doc___": "01",
      "job_type": "NB",
      "self_cert": "Y",
      "block": "01068",
      "lot": "00072",
      "community_board": "501",
      "zip_code": "10302",
      "bldg_type": "2",
      "permit_status": "ISSUED",
      "filing_status": "RENEWAL",
      "permit_type": "NB",
      "permit_sequence__": "03",
      "site_fill": "USE UNDER 300 CU.YD",
      "filing_date": "12/04/2021",
      "issuance_date": "12/04/2021",
      "expiration_date": "01/04/2022",
      "job_start_date": "06/25/2020",
      "permittee_s_first_name": "PHILIP",
      "permittee_s_last_name": "APAP",
      "permittee_s_business_name": "HUDSON RIVER CONTRACTING*",
      "permittee_s_phone__": "8455621350",
      "permittee_s_license_type": "GC",
      "permittee_s_license__": "0610584",
      "superintendent_first___last_name": "PAUL APAP",
      "superintendent_business_name": "HUDSON RIVER CONTRACTING",
      "owner_s_business_type": "CORPORATION",
      "non_profit": "N",
      "owner_s_business_name": "AMERCO REAL ESTATE COMPANY",
      "owner_s_first_name": "CARLOS",
      "owner_s_last_name": "VIZCARRA",
      "permit_si_no": "3883854",
      "gis_latitude": "40.640322",
      "gis_longitude": "-74.133391",
      "gis_council_district": "49",
      "gis_census_tract": "20702",
      "bbl": "5010680072",
      "gis_nta_name": "Port Richmond",
      "dobrundate": "2026-07-05T00:00:00.000"
    },
    {
      "borough": "STATEN ISLAND",
      "bin__": "5107019",
      "house__": "2111",
      "street_name": "RICHMOND TERRACE",
      "job__": "520333559",
      "job_doc___": "03",
      "job_type": "NB",
      "self_cert": "Y",
      "block": "01068",
      "lot": "00072",
      "community_board": "501",
      "zip_code": "10302",
      "bldg_type": "2",
      "work_type": "PL",
      "permit_status": "ISSUED",
      "filing_status": "RENEWAL",
      "permit_type": "PL",
      "permit_sequence__": "02",
      "filing_date": "09/13/2023",
      "issuance_date": "09/13/2023",
      "expiration_date": "09/12/2024",
      "job_start_date": "03/29/2022",
      "permittee_s_first_name": "REDZEP",
      "permittee_s_last_name": "KOSIC",
      "permittee_s_business_name": "FLOW-RIGHT PLBG & HTG COR",
      "permittee_s_phone__": "6469320298",
      "permittee_s_license_type": "MP",
      "permittee_s_license__": "0002295",
      "owner_s_business_type": "CORPORATION",
      "non_profit": "N",
      "owner_s_business_name": "AMERCO REAL ESTATE COMPANY",
      "owner_s_first_name": "CARLOS",
      "owner_s_last_name": "VIZCARRA",
      "permit_si_no": "3961635",
      "gis_latitude": "40.640322",
      "gis_longitude": "-74.133391",
      "gis_council_district": "49",
      "gis_census_tract": "20702",
      "bbl": "5010680072",
      "gis_nta_name": "Port Richmond",
      "dobrundate": "2026-07-05T00:00:00.000"
    },
    {
      "borough": "STATEN ISLAND",
      "bin__": "5107019",
      "house__": "2111",
      "street_name": "RICHMOND TERRACE",
      "job__": "520333559",
      "job_doc___": "02",
      "job_type": "NB",
      "self_cert": "Y",
      "block": "01068",
      "lot": "00072",
      "community_board": "501",
      "zip_code": "10302",
      "bldg_type": "2",
      "work_type": "PL",
      "permit_status": "ISSUED",
      "filing_status": "INITIAL",
      "permit_type": "PL",
      "permit_sequence__": "01",
      "filing_date": "08/25/2020",
      "issuance_date": "08/25/2020",
      "expiration_date": "08/25/2021",
      "job_start_date": "08/25/2020",
      "permittee_s_first_name": "NORMAN",
      "permittee_s_last_name": "SHERMAN",
      "permittee_s_business_name": "RICHMOND CONSTRUCTION & P",
      "permittee_s_phone__": "3479307101",
      "permittee_s_license_type": "MP",
      "permittee_s_license__": "0001006",
      "owner_s_business_type": "CORPORATION",
      "non_profit": "N",
      "owner_s_business_name": "AMERCO REAL ESTATE COMPANY",
      "owner_s_first_name": "CARLOS",
      "owner_s_last_name": "VIZCARRA",
      "permit_si_no": "3784306",
      "gis_latitude": "40.640322",
      "gis_longitude": "-74.133391",
      "gis_council_district": "49",
      "gis_census_tract": "20702",
      "bbl": "5010680072",
      "gis_nta_name": "Port Richmond",
      "dobrundate": "2026-07-05T00:00:00.000"
    },
    {
      "borough": "STATEN ISLAND",
      "bin__": "5107019",
      "house__": "2111",
      "street_name": "RICHMOND TERRACE",
      "job__": "520310850",
      "job_doc___": "01",
      "job_type": "DM",
      "self_cert": "N",
      "block": "01068",
      "lot": "00072",
      "community_board": "501",
      "zip_code": "10302",
      "bldg_type": "2",
      "permit_status": "ISSUED",
      "filing_status": "INITIAL",
      "permit_type": "DM",
      "permit_sequence__": "01",
      "site_fill": "USE UNDER 300 CU.YD",
      "filing_date": "07/13/2018",
      "issuance_date": "07/13/2018",
      "expiration_date": "09/10/2018",
      "job_start_date": "07/13/2018",
      "permittee_s_first_name": "WILLIAM",
      "permittee_s_last_name": "FORMICA",
      "permittee_s_business_name": "FORMICA CONSTRUCTION, INC",
      "permittee_s_phone__": "7187204603",
      "permittee_s_license_type": "GC",
      "permittee_s_license__": "0004146",
      "superintendent_first___last_name": "WILLIAM FORMICA",
      "superintendent_business_name": "FORMICA CONSTRUCTION.INC",
      "owner_s_business_type": "CORPORATION",
      "non_profit": "N",
      "owner_s_business_name": "AMERCO REAL ESTATE COMPANY",
      "owner_s_first_name": "CARLOS",
      "owner_s_last_name": "VIZCARRA",
      "permit_si_no": "3599166",
      "gis_latitude": "40.640322",
      "gis_longitude": "-74.133391",
      "gis_council_district": "49",
      "gis_census_tract": "20702",
      "bbl": "5010680072",
      "gis_nta_name": "Port Richmond",
      "dobrundate": "2026-07-05T00:00:00.000"
    },
    {
      "borough": "STATEN ISLAND",
      "bin__": "5107019",
      "house__": "2111",
      "street_name": "RICHMOND TERRACE",
      "job__": "520310850",
      "job_doc___": "01",
      "job_type": "DM",
      "self_cert": "N",
      "block": "01068",
      "lot": "00072",
      "community_board": "501",
      "zip_code": "10302",
      "bldg_type": "2",
      "work_type": "EQ",
      "permit_status": "ISSUED",
      "filing_status": "INITIAL",
      "permit_type": "EQ",
      "permit_sequence__": "01",
      "permit_subtype": "FN",
      "site_fill": "USE UNDER 300 CU.YD",
      "filing_date": "07/12/2018",
      "issuance_date": "07/12/2018",
      "expiration_date": "07/12/2019",
      "job_start_date": "07/12/2018",
      "permittee_s_first_name": "WILLIAM",
      "permittee_s_last_name": "FORMICA",
      "permittee_s_business_name": "FORMICA CONSTRUCTION, INC",
      "permittee_s_phone__": "7187204603",
      "permittee_s_license_type": "GC",
      "permittee_s_license__": "0004146",
      "owner_s_business_type": "CORPORATION",
      "non_profit": "N",
      "owner_s_business_name": "AMERCO REAL ESTATE COMPANY",
      "owner_s_first_name": "CARLOS",
      "owner_s_last_name": "VIZCARRA",
      "permit_si_no": "3598836",
      "gis_latitude": "40.640322",
      "gis_longitude": "-74.133391",
      "gis_council_district": "49",
      "gis_census_tract": "20702",
      "bbl": "5010680072",
      "gis_nta_name": "Port Richmond",
      "dobrundate": "2026-07-05T00:00:00.000"
    },
    {
      "borough": "STATEN ISLAND",
      "bin__": "5107019",
      "house__": "2111",
      "street_name": "RICHMOND TERRACE",
      "job__": "520333559",
      "job_doc___": "01",
      "job_type": "NB",
      "self_cert": "Y",
      "block": "01068",
      "lot": "00072",
      "community_board": "501",
      "zip_code": "10302",
      "bldg_type": "2",
      "permit_status": "ISSUED",
      "filing_status": "INITIAL",
      "permit_type": "NB",
      "permit_sequence__": "01",
      "site_fill": "USE UNDER 300 CU.YD",
      "filing_date": "06/23/2020",
      "issuance_date": "06/25/2020",
      "expiration_date": "06/25/2021",
      "job_start_date": "06/25/2020",
      "permittee_s_first_name": "PHILIP",
      "permittee_s_last_name": "APAP",
      "permittee_s_business_name": "HUDSON RIVER CONTRACTING*",
      "permittee_s_phone__": "8455621350",
      "permittee_s_license_type": "GC",
      "permittee_s_license__": "0610584",
      "superintendent_first___last_name": "PAUL APAP",
      "superintendent_business_name": "HUDSON RIVER CONTRACTING",
      "owner_s_business_type": "CORPORATION",
      "non_profit": "N",
      "owner_s_business_name": "AMERCO REAL ESTATE COMPANY",
      "owner_s_first_name": "CARLOS",
      "owner_s_last_name": "VIZCARRA",
      "permit_si_no": "3765833",
      "gis_latitude": "40.640322",
      "gis_longitude": "-74.133391",
      "gis_council_district": "49",
      "gis_census_tract": "20702",
      "bbl": "5010680072",
      "gis_nta_name": "Port Richmond",
      "dobrundate": "2026-07-05T00:00:00.000"
    },
    {
      "borough": "STATEN ISLAND",
      "bin__": "5107019",
      "house__": "2111",
      "street_name": "RICHMOND TERRACE",
      "job__": "520333559",
      "job_doc___": "01",
      "job_type": "NB",
      "self_cert": "Y",
      "block": "01068",
      "lot": "00072",
      "community_board": "501",
      "zip_code": "10302",
      "bldg_type": "2",
      "permit_status": "ISSUED",
      "filing_status": "RENEWAL",
      "permit_type": "NB",
      "permit_sequence__": "02",
      "site_fill": "USE UNDER 300 CU.YD",
      "filing_date": "05/28/2021",
      "issuance_date": "05/28/2021",
      "expiration_date": "01/04/2022",
      "job_start_date": "06/25/2020",
      "permittee_s_first_name": "PHILIP",
      "permittee_s_last_name": "APAP",
      "permittee_s_business_name": "HUDSON RIVER CONTRACTING*",
      "permittee_s_phone__": "8455621350",
      "permittee_s_license_type": "GC",
      "permittee_s_license__": "0610584",
      "superintendent_first___last_name": "PAUL APAP",
      "superintendent_business_name": "HUDSON RIVER CONTRACTING",
      "owner_s_business_type": "CORPORATION",
      "non_profit": "N",
      "owner_s_business_name": "AMERCO REAL ESTATE COMPANY",
      "owner_s_first_name": "CARLOS",
      "owner_s_last_name": "VIZCARRA",
      "permit_si_no": "3852195",
      "gis_latitude": "40.640322",
      "gis_longitude": "-74.133391",
      "gis_council_district": "49",
      "gis_census_tract": "20702",
      "bbl": "5010680072",
      "gis_nta_name": "Port Richmond",
      "dobrundate": "2026-07-05T00:00:00.000"
    },
    {
      "borough": "STATEN ISLAND",
      "bin__": "5107019",
      "house__": "2111",
      "street_name": "RICHMOND TERRACE",
      "job__": "520333559",
      "job_doc___": "01",
      "job_type": "NB",
      "self_cert": "Y",
      "block": "01068",
      "lot": "00072",
      "community_board": "501",
      "zip_code": "10302",
      "bldg_type": "2",
      "permit_status": "ISSUED",
      "filing_status": "RENEWAL",
      "permit_type": "NB",
      "permit_sequence__": "07",
      "site_fill": "USE UNDER 300 CU.YD",
      "filing_date": "04/24/2023",
      "issuance_date": "04/24/2023",
      "expiration_date": "01/04/2024",
      "job_start_date": "06/25/2020",
      "permittee_s_first_name": "PHILIP",
      "permittee_s_last_name": "APAP",
      "permittee_s_business_name": "HUDSON RIVER CONTRACTING*",
      "permittee_s_phone__": "8455621350",
      "permittee_s_license_type": "GC",
      "permittee_s_license__": "0610584",
      "superintendent_first___last_name": "PAUL APAP",
      "superintendent_business_name": "HUDSON RIVER CONTRACTING",
      "owner_s_business_type": "CORPORATION",
      "non_profit": "N",
      "owner_s_business_name": "AMERCO REAL ESTATE COMPANY",
      "owner_s_first_name": "CARLOS",
      "owner_s_last_name": "VIZCARRA",
      "permit_si_no": "3947933",
      "gis_latitude": "40.640322",
      "gis_longitude": "-74.133391",
      "gis_council_district": "49",
      "gis_census_tract": "20702",
      "bbl": "5010680072",
      "gis_nta_name": "Port Richmond",
      "dobrundate": "2026-07-05T00:00:00.000"
    },
    {
      "borough": "STATEN ISLAND",
      "bin__": "5107019",
      "house__": "2111",
      "street_name": "RICHMOND TERRACE",
      "job__": "520333559",
      "job_doc___": "01",
      "job_type": "NB",
      "self_cert": "Y",
      "block": "01068",
      "lot": "00072",
      "community_board": "501",
      "zip_code": "10302",
      "bldg_type": "2",
      "permit_status": "ISSUED",
      "filing_status": "RENEWAL",
      "permit_type": "NB",
      "permit_sequence__": "05",
      "site_fill": "USE UNDER 300 CU.YD",
      "filing_date": "04/06/2022",
      "issuance_date": "04/06/2022",
      "expiration_date": "01/04/2023",
      "job_start_date": "06/25/2020",
      "permittee_s_first_name": "PHILIP",
      "permittee_s_last_name": "APAP",
      "permittee_s_business_name": "HUDSON RIVER CONTRACTING*",
      "permittee_s_phone__": "8455621350",
      "permittee_s_license_type": "GC",
      "permittee_s_license__": "0610584",
      "superintendent_first___last_name": "PAUL APAP",
      "superintendent_business_name": "HUDSON RIVER CONTRACTING",
      "owner_s_business_type": "CORPORATION",
      "non_profit": "N",
      "owner_s_business_name": "AMERCO REAL ESTATE COMPANY",
      "owner_s_first_name": "CARLOS",
      "owner_s_last_name": "VIZCARRA",
      "permit_si_no": "3902019",
      "gis_latitude": "40.640322",
      "gis_longitude": "-74.133391",
      "gis_council_district": "49",
      "gis_census_tract": "20702",
      "bbl": "5010680072",
      "gis_nta_name": "Port Richmond",
      "dobrundate": "2026-07-05T00:00:00.000"
    },
    {
      "borough": "STATEN ISLAND",
      "bin__": "5107019",
      "house__": "2111",
      "street_name": "RICHMOND TERRACE",
      "job__": "520333559",
      "job_doc___": "03",
      "job_type": "NB",
      "self_cert": "Y",
      "block": "01068",
      "lot": "00072",
      "community_board": "501",
      "zip_code": "10302",
      "bldg_type": "2",
      "work_type": "PL",
      "permit_status": "ISSUED",
      "filing_status": "INITIAL",
      "permit_type": "PL",
      "permit_sequence__": "01",
      "filing_date": "03/22/2022",
      "issuance_date": "03/22/2022",
      "expiration_date": "03/22/2023",
      "job_start_date": "03/29/2022",
      "permittee_s_first_name": "REDZEP",
      "permittee_s_last_name": "KOSIC",
      "permittee_s_business_name": "FLOW-RIGHT PLBG & HTG COR",
      "permittee_s_phone__": "7185241020",
      "permittee_s_license_type": "MP",
      "permittee_s_license__": "0002295",
      "owner_s_business_type": "CORPORATION",
      "non_profit": "N",
      "owner_s_business_name": "AMERCO REAL ESTATE COMPANY",
      "owner_s_first_name": "CARLOS",
      "owner_s_last_name": "VIZCARRA",
      "permit_si_no": "3899401",
      "gis_latitude": "40.640322",
      "gis_longitude": "-74.133391",
      "gis_council_district": "49",
      "gis_census_tract": "20702",
      "bbl": "5010680072",
      "gis_nta_name": "Port Richmond",
      "dobrundate": "2026-07-05T00:00:00.000"
    },
    {
      "borough": "STATEN ISLAND",
      "bin__": "5107019",
      "house__": "2111",
      "street_name": "RICHMOND TERRACE",
      "job__": "520333559",
      "job_doc___": "01",
      "job_type": "NB",
      "self_cert": "Y",
      "block": "01068",
      "lot": "00072",
      "community_board": "501",
      "zip_code": "10302",
      "bldg_type": "2",
      "permit_status": "ISSUED",
      "filing_status": "RENEWAL",
      "permit_type": "NB",
      "permit_sequence__": "06",
      "site_fill": "USE UNDER 300 CU.YD",
      "filing_date": "01/04/2023",
      "issuance_date": "01/04/2023",
      "expiration_date": "04/01/2023",
      "job_start_date": "06/25/2020",
      "permittee_s_first_name": "PHILIP",
      "permittee_s_last_name": "APAP",
      "permittee_s_business_name": "HUDSON RIVER CONTRACTING*",
      "permittee_s_phone__": "8455621350",
      "permittee_s_license_type": "GC",
      "permittee_s_license__": "0610584",
      "superintendent_first___last_name": "PAUL APAP",
      "superintendent_business_name": "HUDSON RIVER CONTRACTING",
      "owner_s_business_type": "CORPORATION",
      "non_profit": "N",
      "owner_s_business_name": "AMERCO REAL ESTATE COMPANY",
      "owner_s_first_name": "CARLOS",
      "owner_s_last_name": "VIZCARRA",
      "permit_si_no": "3935416",
      "gis_latitude": "40.640322",
      "gis_longitude": "-74.133391",
      "gis_council_district": "49",
      "gis_census_tract": "20702",
      "bbl": "5010680072",
      "gis_nta_name": "Port Richmond",
      "dobrundate": "2026-07-05T00:00:00.000"
    }
  ]
}