{
  "key": "https://data.cityofnewyork.us/resource/5zyy-y8am.json?nyc_borough_block_and_lot=3009810111&%24order=report_year+DESC&%24limit=10&%24%24app_token=kp5QgrwF887lu2gNqvS0BEozO",
  "recordedAt": "2026-06-07T13:58:53.381Z",
  "value": [
    {
      "report_year": "2024",
      "property_id": "1633962",
      "property_name": "K051 (OECID: 0300071; BBL: 3009810111)",
      "parent_property_id": "Not Applicable: Standalone Property",
      "parent_property_name": "Not Applicable: Standalone Property",
      "year_ending": "2024-12-31T00:00:00.000",
      "nyc_borough_block_and_lot": "3009810111",
      "nyc_building_identification": "3021057",
      "address_1": "350 5th Avenue",
      "city": "Brooklyn",
      "postal_code": "11215",
      "primary_property_type_self": "K-12 School",
      "primary_property_type": "K-12 School",
      "national_median_reference": "CBECS - Elementary/Middle & High School",
      "list_of_all_property_use": "K-12 School (135600.0)",
      "largest_property_use_type": "K-12 School",
      "largest_property_use_type_1": "135600",
      "_2nd_largest_property_use": "Not Available",
      "_2nd_largest_property_use_1": "Not Available",
      "_3rd_largest_property_use": "Not Available",
      "_3rd_largest_property_use_1": "Not Available",
      "year_built": "1950",
      "construction_status": "Existing",
      "number_of_buildings": "1",
      "occupancy": "100",
      "metered_areas_energy": "Whole Property",
      "energy_star_score": "83",
      "national_median_energy_star": "50",
      "target_energy_star_score": "75",
      "reason_s_for_no_score": "Not Available",
      "energy_star_certification": "Not Available",
      "eligible_for_certification_for_report_ped_y_n_": "No",
      "energy_star_certification_1": "Not Available",
      "energy_star_certification_application_status": "Not Available",
      "site_eui_kbtu_ft": "55.8",
      "weather_normalized_site_eui": "57.4",
      "national_median_site_eui": "83.5",
      "site_energy_use_kbtu": "7572875.1",
      "weather_normalized_site_energy": "7786880.4",
      "electricity_weather_normalized": "530100",
      "electricity_weather_normalized_1": "3.9",
      "percent_electricity": "23.9",
      "natural_gas_weather_normalized": "2134",
      "natural_gas_weather_normalized_1": "0",
      "source_eui_kbtu_ft": "80.3",
      "weather_normalized_source": "81.9",
      "national_median_source_eui": "120.1",
      "source_energy_use_kbtu": "10894714.9",
      "weather_normalized_source_1": "11110860.3",
      "fuel_oil_1_use_kbtu": "Not Available",
      "fuel_oil_2_use_kbtu": "Not Available",
      "fuel_oil_4_use_kbtu": "5550773.9",
      "fuel_oil_5_6_use_kbtu": "Not Available",
      "diesel_2_use_kbtu": "Not Available",
      "propane_use_kbtu": "Not Available",
      "kerosene_use_kbtu": "Not Available",
      "district_steam_use_kbtu": "Not Available",
      "district_hot_water_use_kbtu": "Not Available",
      "district_chilled_water_use": "Not Available",
      "natural_gas_use_kbtu": "213400",
      "natural_gas_use_therms_": "2134",
      "electricity_use_grid_purchase": "1808701.2",
      "electricity_use_grid_purchase_1": "530100",
      "electricity_use_grid_purchase_2": "530100",
      "electricity_use_grid_purchase_3": "1808701.2",
      "electricity_use_generated": "Not Available",
      "electricity_use_generated_1": "Not Available",
      "electricity_use_generated_2": "Not Available",
      "electricity_use_generated_3": "Not Available",
      "annual_maximum_demand_kw": "271.7",
      "annual_maximum_demand_mm": "06/2024",
      "annual_maximum_demand_meter": "0300071E (7875870)",
      "green_power_onsite_kwh": "Not Available",
      "green_power_offsite_kwh": "0",
      "green_power_onsite_and_offsite": "0",
      "total_location_based_ghg": "637.37",
      "total_location_based_ghg_1": "4.7",
      "direct_ghg_emissions_metric": "429.21",
      "direct_ghg_emissions_intensity": "3.17",
      "indirect_location_based_ghg": "208.16",
      "indirect_location_based_ghg_1": "1.54",
      "national_median_total_location": "953.07",
      "avoided_emissions_onsite": "Not Available",
      "avoided_emissions_offsite": "0",
      "avoided_emissions_onsite_1": "0",
      "percent_of_electricity_that": "0",
      "percent_of_recs_retained": "Not Available",
      "percent_of_total_electricity": "Not Available",
      "leed_us_project_id": "Not Available",
      "default_values": "No",
      "temporary_values": "false",
      "estimated_values_energy": "No",
      "estimated_values_water": "No",
      "alert_energy_meter_has_less": "Ok",
      "alert_energy_meter_has_gaps": "Ok",
      "alert_energy_meter_has": "Ok",
      "alert_energy_no_meters": "Ok",
      "alert_energy_meter_has_single": "Ok",
      "alert_property_has_no_uses": "Ok",
      "alert_water_meter_has_less": "Ok",
      "alert_data_center_issue_with": "Ok",
      "alert_gross_floor_area_is": "Ok",
      "estimated_data_flag": "No",
      "estimated_data_flag_natural": "No",
      "estimated_data_flag_district": "Not Available",
      "estimated_data_flag_1": "Not Available",
      "estimated_data_flag_fuel": "Not Available",
      "estimated_data_flag_fuel_1": "Not Available",
      "estimated_data_flag_fuel_2": "No",
      "estimated_data_flag_fuel_3": "Not Available",
      "estimated_data_flag_diesel": "Not Available",
      "estimated_data_flag_2": "Not Available",
      "data_center_ups_output_meter": "Not Available",
      "data_center_pdu_input_meter": "Not Available",
      "data_center_pdu_output_meter": "Not Available",
      "data_center_it_equipment": "Not Available",
      "data_center_it_site_energy": "Not Available",
      "data_center_it_source_energy": "Not Available",
      "data_center_pue": "Not Available",
      "data_center_national_median": "Not Available",
      "data_center_gross_floor_area": "Not Available",
      "data_center_ups_system": "Not Available",
      "data_center_it_energy": "Not Available",
      "data_center_energy_estimates": "Not Available",
      "data_center_cooling_equipment": "Not Available",
      "adult_education_gross_floor": "Not Available",
      "ambulatory_surgical_center": "Not Available",
      "automobile_dealership_gross": "Not Available",
      "bank_branch_gross_floor_area": "Not Available",
      "barracks_gross_floor_area": "Not Available",
      "college_university_gross": "Not Available",
      "convention_center_gross_floor": "Not Available",
      "courthouse_gross_floor_area": "Not Available",
      "distribution_center_gross": "Not Available",
      "enclosed_mall_gross_floor": "Not Available",
      "energy_power_station_gross": "Not Available",
      "financial_office_gross_floor": "Not Available",
      "financial_office_number_of": "Not Available",
      "financial_office_weekly": "Not Available",
      "financial_office_number_of_1": "Not Available",
      "fitness_center_health_club": "Not Available",
      "food_sales_gross_floor_area": "Not Available",
      "food_service_gross_floor": "Not Available",
      "hospital_general_medical": "Not Available",
      "hospital_general_medical_1": "Not Available",
      "hospital_general_medical_2": "Not Available",
      "hospital_general_medical_3": "Not Available",
      "hospital_general_medical_4": "Not Available",
      "hospital_general_medical_5": "Not Available",
      "hospital_general_medical_6": "Not Available",
      "hospital_general_medical_7": "Not Available",
      "hospital_general_medical_8": "Not Available",
      "hospital_general_medical_9": "Not Available",
      "hospital_general_medical_10": "Not Available",
      "medical_office_gross_floor": "Not Available",
      "medical_office_number_of": "Not Available",
      "medical_office_number_of_1": "Not Available",
      "medical_office_number_of_2": "Not Available",
      "medical_office_percent_that": "Not Available",
      "medical_office_percent_that_1": "Not Available",
      "medical_office_weekly": "Not Available",
      "outpatient_rehabilitation": "Not Available",
      "urgent_care_clinic_other": "Not Available",
      "hotel_gross_floor_area_ft": "Not Available",
      "hotel_gym_fitness_center": "Not Available",
      "k_12_school_gross_floor_area": "135600",
      "pre_school_daycare_gross": "Not Available",
      "laboratory_gross_floor_area": "Not Available",
      "mailing_center_post_office": "Not Available",
      "movie_theater_gross_floor": "Not Available",
      "manufacturing_industrial": "Not Available",
      "multifamily_housing_government": "Not Available",
      "institutional_property_y_n_": "Not Available",
      "multifamily_housing_gross": "Not Available",
      "multifamily_housing_number": "Not Available",
      "multifamily_housing_number_1": "Not Available",
      "multifamily_housing_number_2": "Not Available",
      "multifamily_housing_number_3": "Not Available",
      "multifamily_housing_number_4": "Not Available",
      "multifamily_housing_percent": "Not Available",
      "multifamily_housing_percent_1": "Not Available",
      "multifamily_housing_total": "Not Available",
      "multifamily_housing_total_1": "Not Available",
      "multifamily_housing_number_5": "Not Available",
      "multifamily_housing_number_6": "Not Available",
      "multifamily_housing_number_7": "Not Available",
      "multifamily_housing_resident": "Not Available",
      "residence_hall_dormitory": "Not Available",
      "refrigerated_warehouse_gross": "Not Available",
      "non_refrigerated_warehouse": "Not Available",
      "office_gross_floor_area_ft": "Not Available",
      "office_number_of_computers": "Not Available",
      "office_number_of_workers": "Not Available",
      "office_percent_that_can_be": "Not Available",
      "office_percent_that_can_be_1": "Not Available",
      "office_weekly_operating_hours": "Not Available",
      "office_worker_density_number": "Not Available",
      "other_gross_floor_area_ft": "Not Available",
      "museum_gross_floor_area_ft": "Not Available",
      "performing_arts_gross_floor": "Not Available",
      "parking_gross_floor_area": "Not Available",
      "parking_open_parking_lot": "Not Available",
      "parking_completely_enclosed": "Not Available",
      "parking_partially_enclosed": "Not Available",
      "restaurant_gross_floor_area": "Not Available",
      "restaurant_weekly_operating": "Not Available",
      "restaurant_worker_density": "Not Available",
      "retail_store_gross_floor": "Not Available",
      "retail_store_number_of_walk": "Not Available",
      "retail_store_number_of_open": "Not Available",
      "self_storage_facility_gross": "Not Available",
      "senior_living_community_gross": "Not Available",
      "senior_living_community_living": "Not Available",
      "social_meeting_hall_gross": "Not Available",
      "supermarket_grocery_gross": "Not Available",
      "supermarket_grocery_number": "Not Available",
      "supermarket_grocery_number_1": "Not Available",
      "wholesale_club_supercenter": "Not Available",
      "wholesale_club_supercenter_1": "Not Available",
      "wastewater_treatment_plant": "Not Available",
      "worship_facility_gross_floor": "Not Available",
      "strip_mall_gross_floor_area": "Not Available",
      "property_gfa_self_reported": "135600",
      "property_gfa_calculated": "135600",
      "property_gfa_calculated_1": "135600",
      "property_gfa_calculated_2": "Not Available",
      "property_notes": "Not Available",
      "water_use_all_water_sources": "899.5",
      "indoor_water_use_all_water": "899.5",
      "outdoor_water_use_all_water": "Not Available",
      "municipally_supplied_potable": "Not Available",
      "municipally_supplied_potable_1": "899.5",
      "municipally_supplied_potable_2": "899.5",
      "municipally_supplied_potable_3": "Not Available",
      "third_party_certification": "Not Available",
      "third_party_certification_1": "Not Available",
      "third_party_certification_2": "Not Available",
      "data_quality_checker_run_": "No",
      "data_quality_checker_date_run": "Not Available",
      "electric_distribution_utility": "Consolidated Edison Co-NY Inc",
      "number_of_active_energy_meters": "3",
      "number_of_active_energy_meters_1": "3",
      "number_of_active_energy_meters_2": "0",
      "number_of_active_it_meters": "0",
      "aggregate_meter_s_electric_number_of_individual_meters_included": "0",
      "aggregate_meter_s_natural_gas_number_of_individual_meters_included": "0",
      "aggregate_meter_s_district_steam_number_of_individual_meters_included": "0",
      "report_generation_date": "2025-08-30T00:00:00.000",
      "borough": "BROOKLYN",
      "latitude": "40.672015",
      "longitude": "-73.983947",
      "community_board": "306",
      "council_district": "39",
      "ct2020": "135",
      "nta2020": "BK0602"
    },
    {
      "report_year": "2023",
      "property_id": "1633962",
      "property_name": "K051 (OECID: 0300071; BBL: 3009810111)",
      "parent_property_id": "Not Applicable: Standalone Property",
      "parent_property_name": "Not Applicable: Standalone Property",
      "year_ending": "2023-12-31T00:00:00.000",
      "nyc_borough_block_and_lot": "3009810111",
      "nyc_building_identification": "3021057",
      "address_1": "350 5th Avenue",
      "city": "Brooklyn",
      "postal_code": "11215",
      "primary_property_type_self": "K-12 School",
      "primary_property_type": "K-12 School",
      "national_median_reference": "CBECS - Elementary/Middle & High School",
      "list_of_all_property_use": "K-12 School (135600.0)",
      "largest_property_use_type": "K-12 School",
      "largest_property_use_type_1": "135600",
      "_2nd_largest_property_use": "Not Available",
      "_2nd_largest_property_use_1": "Not Available",
      "_3rd_largest_property_use": "Not Available",
      "_3rd_largest_property_use_1": "Not Available",
      "year_built": "1950",
      "construction_status": "Existing",
      "number_of_buildings": "1",
      "occupancy": "100",
      "metered_areas_energy": "Whole Property",
      "energy_star_score": "80",
      "national_median_energy_star": "50",
      "target_energy_star_score": "75",
      "reason_s_for_no_score": "Not Available",
      "energy_star_certification": "Not Available",
      "eligible_for_certification_for_report_ped_y_n_": "No",
      "energy_star_certification_1": "Not Available",
      "energy_star_certification_application_status": "Not Available",
      "site_eui_kbtu_ft": "62.1",
      "weather_normalized_site_eui": "70.3",
      "national_median_site_eui": "88.8",
      "site_energy_use_kbtu": "8426885.7",
      "weather_normalized_site_energy": "9529234.3",
      "electricity_weather_normalized": "457488.9",
      "electricity_weather_normalized_1": "3.4",
      "percent_electricity": "18.5",
      "natural_gas_weather_normalized": "1511",
      "natural_gas_weather_normalized_1": "0",
      "source_eui_kbtu_ft": "83.4",
      "weather_normalized_source": "91.6",
      "national_median_source_eui": "119.1",
      "source_energy_use_kbtu": "11311303.5",
      "weather_normalized_source_1": "12424675.6",
      "fuel_oil_1_use_kbtu": "Not Available",
      "fuel_oil_2_use_kbtu": "Not Available",
      "fuel_oil_4_use_kbtu": "6714833.2",
      "fuel_oil_5_6_use_kbtu": "Not Available",
      "diesel_2_use_kbtu": "Not Available",
      "propane_use_kbtu": "Not Available",
      "kerosene_use_kbtu": "Not Available",
      "district_steam_use_kbtu": "Not Available",
      "district_hot_water_use_kbtu": "Not Available",
      "district_chilled_water_use": "Not Available",
      "natural_gas_use_kbtu": "151100",
      "natural_gas_use_therms_": "1511",
      "electricity_use_grid_purchase": "1560952.5",
      "electricity_use_grid_purchase_1": "457488.9",
      "electricity_use_grid_purchase_2": "457489",
      "electricity_use_grid_purchase_3": "1560952.5",
      "electricity_use_generated": "Not Available",
      "electricity_use_generated_1": "Not Available",
      "electricity_use_generated_2": "Not Available",
      "electricity_use_generated_3": "Not Available",
      "annual_maximum_demand_kw": "280",
      "annual_maximum_demand_mm": "09/2023",
      "annual_maximum_demand_meter": "0300071E (7875870)",
      "green_power_onsite_kwh": "Not Available",
      "green_power_offsite_kwh": "0",
      "green_power_onsite_and_offsite": "0",
      "total_location_based_ghg": "683.3",
      "total_location_based_ghg_1": "5",
      "direct_ghg_emissions_metric": "513.6",
      "direct_ghg_emissions_intensity": "3.8",
      "indirect_location_based_ghg": "169.7",
      "indirect_location_based_ghg_1": "1.3",
      "national_median_total_location": "975.9",
      "avoided_emissions_onsite": "Not Available",
      "avoided_emissions_offsite": "0",
      "avoided_emissions_onsite_1": "0",
      "percent_of_electricity_that": "0",
      "percent_of_recs_retained": "Not Available",
      "percent_of_total_electricity": "Not Available",
      "leed_us_project_id": "Not Available",
      "default_values": "No",
      "temporary_values": "false",
      "estimated_values_energy": "No",
      "estimated_values_water": "No",
      "alert_energy_meter_has_less": "Ok",
      "alert_energy_meter_has_gaps": "Ok",
      "alert_energy_meter_has": "Ok",
      "alert_energy_no_meters": "Ok",
      "alert_energy_meter_has_single": "Ok",
      "alert_property_has_no_uses": "Ok",
      "alert_water_meter_has_less": "Ok",
      "alert_data_center_issue_with": "Ok",
      "alert_gross_floor_area_is": "Ok",
      "estimated_data_flag": "No",
      "estimated_data_flag_natural": "No",
      "estimated_data_flag_district": "Not Available",
      "estimated_data_flag_1": "Not Available",
      "estimated_data_flag_fuel": "Not Available",
      "estimated_data_flag_fuel_1": "Not Available",
      "estimated_data_flag_fuel_2": "No",
      "estimated_data_flag_fuel_3": "Not Available",
      "estimated_data_flag_diesel": "Not Available",
      "estimated_data_flag_2": "Not Available",
      "data_center_ups_output_meter": "Not Available",
      "data_center_pdu_input_meter": "Not Available",
      "data_center_pdu_output_meter": "Not Available",
      "data_center_it_equipment": "Not Available",
      "data_center_it_site_energy": "Not Available",
      "data_center_it_source_energy": "Not Available",
      "data_center_pue": "Not Available",
      "data_center_national_median": "Not Available",
      "data_center_gross_floor_area": "Not Available",
      "data_center_ups_system": "Not Available",
      "data_center_it_energy": "Not Available",
      "data_center_energy_estimates": "Not Available",
      "data_center_cooling_equipment": "Not Available",
      "adult_education_gross_floor": "Not Available",
      "ambulatory_surgical_center": "Not Available",
      "automobile_dealership_gross": "Not Available",
      "bank_branch_gross_floor_area": "Not Available",
      "barracks_gross_floor_area": "Not Available",
      "college_university_gross": "Not Available",
      "convention_center_gross_floor": "Not Available",
      "courthouse_gross_floor_area": "Not Available",
      "distribution_center_gross": "Not Available",
      "enclosed_mall_gross_floor": "Not Available",
      "energy_power_station_gross": "Not Available",
      "financial_office_gross_floor": "Not Available",
      "financial_office_number_of": "Not Available",
      "financial_office_weekly": "Not Available",
      "financial_office_number_of_1": "Not Available",
      "fitness_center_health_club": "Not Available",
      "food_sales_gross_floor_area": "Not Available",
      "food_service_gross_floor": "Not Available",
      "hospital_general_medical": "Not Available",
      "hospital_general_medical_1": "Not Available",
      "hospital_general_medical_2": "Not Available",
      "hospital_general_medical_3": "Not Available",
      "hospital_general_medical_4": "Not Available",
      "hospital_general_medical_5": "Not Available",
      "hospital_general_medical_6": "Not Available",
      "hospital_general_medical_7": "Not Available",
      "hospital_general_medical_8": "Not Available",
      "hospital_general_medical_9": "Not Available",
      "hospital_general_medical_10": "Not Available",
      "medical_office_gross_floor": "Not Available",
      "medical_office_number_of": "Not Available",
      "medical_office_number_of_1": "Not Available",
      "medical_office_number_of_2": "Not Available",
      "medical_office_percent_that": "Not Available",
      "medical_office_percent_that_1": "Not Available",
      "medical_office_weekly": "Not Available",
      "outpatient_rehabilitation": "Not Available",
      "urgent_care_clinic_other": "Not Available",
      "hotel_gross_floor_area_ft": "Not Available",
      "hotel_gym_fitness_center": "Not Available",
      "k_12_school_gross_floor_area": "135600",
      "pre_school_daycare_gross": "Not Available",
      "laboratory_gross_floor_area": "Not Available",
      "mailing_center_post_office": "Not Available",
      "movie_theater_gross_floor": "Not Available",
      "manufacturing_industrial": "Not Available",
      "multifamily_housing_government": "Not Available",
      "institutional_property_y_n_": "Not Available",
      "multifamily_housing_gross": "Not Available",
      "multifamily_housing_number": "Not Available",
      "multifamily_housing_number_1": "Not Available",
      "multifamily_housing_number_2": "Not Available",
      "multifamily_housing_number_3": "Not Available",
      "multifamily_housing_number_4": "Not Available",
      "multifamily_housing_percent": "Not Available",
      "multifamily_housing_percent_1": "Not Available",
      "multifamily_housing_total": "Not Available",
      "multifamily_housing_total_1": "Not Available",
      "multifamily_housing_number_5": "Not Available",
      "multifamily_housing_number_6": "Not Available",
      "multifamily_housing_number_7": "Not Available",
      "multifamily_housing_resident": "Not Available",
      "residence_hall_dormitory": "Not Available",
      "refrigerated_warehouse_gross": "Not Available",
      "non_refrigerated_warehouse": "Not Available",
      "office_gross_floor_area_ft": "Not Available",
      "office_number_of_computers": "Not Available",
      "office_number_of_workers": "Not Available",
      "office_percent_that_can_be": "Not Available",
      "office_percent_that_can_be_1": "Not Available",
      "office_weekly_operating_hours": "Not Available",
      "office_worker_density_number": "Not Available",
      "other_gross_floor_area_ft": "Not Available",
      "museum_gross_floor_area_ft": "Not Available",
      "performing_arts_gross_floor": "Not Available",
      "parking_gross_floor_area": "Not Available",
      "parking_open_parking_lot": "Not Available",
      "parking_completely_enclosed": "Not Available",
      "parking_partially_enclosed": "Not Available",
      "restaurant_gross_floor_area": "Not Available",
      "restaurant_weekly_operating": "Not Available",
      "restaurant_worker_density": "Not Available",
      "retail_store_gross_floor": "Not Available",
      "retail_store_number_of_walk": "Not Available",
      "retail_store_number_of_open": "Not Available",
      "self_storage_facility_gross": "Not Available",
      "senior_living_community_gross": "Not Available",
      "senior_living_community_living": "Not Available",
      "social_meeting_hall_gross": "Not Available",
      "supermarket_grocery_gross": "Not Available",
      "supermarket_grocery_number": "Not Available",
      "supermarket_grocery_number_1": "Not Available",
      "wholesale_club_supercenter": "Not Available",
      "wholesale_club_supercenter_1": "Not Available",
      "wastewater_treatment_plant": "Not Available",
      "worship_facility_gross_floor": "Not Available",
      "strip_mall_gross_floor_area": "Not Available",
      "property_gfa_self_reported": "135600",
      "property_gfa_calculated": "135600",
      "property_gfa_calculated_1": "135600",
      "property_gfa_calculated_2": "Not Available",
      "property_notes": "Not Available",
      "water_use_all_water_sources": "827.7",
      "indoor_water_use_all_water": "827.7",
      "outdoor_water_use_all_water": "Not Available",
      "municipally_supplied_potable": "Not Available",
      "municipally_supplied_potable_1": "827.7",
      "municipally_supplied_potable_2": "827.7",
      "municipally_supplied_potable_3": "Not Available",
      "third_party_certification": "Not Available",
      "third_party_certification_1": "Not Available",
      "third_party_certification_2": "Not Available",
      "data_quality_checker_run_": "No",
      "data_quality_checker_date_run": "Not Available",
      "electric_distribution_utility": "Consolidated Edison Co-NY Inc",
      "number_of_active_energy_meters": "3",
      "number_of_active_energy_meters_1": "3",
      "number_of_active_energy_meters_2": "0",
      "number_of_active_it_meters": "0",
      "aggregate_meter_s_electric_number_of_individual_meters_included": "0",
      "aggregate_meter_s_natural_gas_number_of_individual_meters_included": "0",
      "aggregate_meter_s_district_steam_number_of_individual_meters_included": "0",
      "report_generation_date": "2024-05-01T16:42:06.193",
      "report_submission_date": "2024-05-01T16:46:29.000",
      "borough": "BROOKLYN",
      "latitude": "40.672015",
      "longitude": "-73.983947",
      "community_board": "306",
      "council_district": "39",
      "ct2020": "135",
      "nta2020": "BK0602"
    },
    {
      "report_year": "2022",
      "property_id": "1633962",
      "property_name": "K051 (OECID: 0300071; BBL: 3009810111)",
      "parent_property_id": "Not Applicable: Standalone Property",
      "parent_property_name": "Not Applicable: Standalone Property",
      "year_ending": "2022-12-31T00:00:00.000",
      "nyc_borough_block_and_lot": "3009810111",
      "nyc_building_identification": "3021057",
      "address_1": "350 5th Avenue",
      "city": "Brooklyn",
      "postal_code": "11215",
      "primary_property_type_self": "K-12 School",
      "primary_property_type": "K-12 School",
      "national_median_reference": "CBECS - Elementary/Middle & High School",
      "list_of_all_property_use": "K-12 School (135600.0)",
      "largest_property_use_type": "K-12 School",
      "largest_property_use_type_1": "135600",
      "_2nd_largest_property_use": "Not Available",
      "_2nd_largest_property_use_1": "Not Available",
      "_3rd_largest_property_use": "Not Available",
      "_3rd_largest_property_use_1": "Not Available",
      "year_built": "1950",
      "construction_status": "Existing",
      "number_of_buildings": "1",
      "occupancy": "100",
      "metered_areas_energy": "Whole Property",
      "energy_star_score": "92",
      "national_median_energy_star": "50",
      "target_energy_star_score": "75",
      "reason_s_for_no_score": "Not Available",
      "energy_star_certification": "Not Available",
      "energy_star_certification_1": "Not Available",
      "site_eui_kbtu_ft": "45.9",
      "weather_normalized_site_eui": "47.7",
      "national_median_site_eui": "84.3",
      "site_energy_use_kbtu": "6217418.5",
      "weather_normalized_site_energy": "6470711.8",
      "electricity_weather_normalized": "504800",
      "electricity_weather_normalized_1": "3.7",
      "natural_gas_weather_normalized": "1085",
      "natural_gas_weather_normalized_1": "0",
      "source_eui_kbtu_ft": "69.1",
      "weather_normalized_source": "71",
      "national_median_source_eui": "127",
      "source_energy_use_kbtu": "9366988.7",
      "weather_normalized_source_1": "9622814.9",
      "fuel_oil_1_use_kbtu": "Not Available",
      "fuel_oil_2_use_kbtu": "Not Available",
      "fuel_oil_4_use_kbtu": "4386540.9",
      "fuel_oil_5_6_use_kbtu": "Not Available",
      "diesel_2_use_kbtu": "Not Available",
      "propane_use_kbtu": "Not Available",
      "kerosene_use_kbtu": "Not Available",
      "district_steam_use_kbtu": "Not Available",
      "district_hot_water_use_kbtu": "Not Available",
      "district_chilled_water_use": "Not Available",
      "natural_gas_use_kbtu": "108500",
      "electricity_use_grid_purchase": "1722377.6",
      "electricity_use_grid_purchase_1": "504800",
      "electricity_use_grid_purchase_2": "504800",
      "electricity_use_grid_purchase_3": "1722377.6",
      "electricity_use_generated": "Not Available",
      "electricity_use_generated_1": "Not Available",
      "electricity_use_generated_2": "Not Available",
      "electricity_use_generated_3": "Not Available",
      "annual_maximum_demand_kw": "232",
      "annual_maximum_demand_mm": "May-22",
      "annual_maximum_demand_meter": "0300071E (7875870)",
      "green_power_onsite_kwh": "Not Available",
      "green_power_offsite_kwh": "0",
      "green_power_onsite_and_offsite": "0",
      "total_location_based_ghg": "481.6",
      "total_location_based_ghg_1": "3.6",
      "direct_ghg_emissions_metric": "336",
      "direct_ghg_emissions_intensity": "2.5",
      "indirect_location_based_ghg": "145.6",
      "indirect_location_based_ghg_1": "1.1",
      "net_emissions_metric_tons": "481.6",
      "national_median_total_location": "885.8",
      "avoided_emissions_onsite": "Not Available",
      "avoided_emissions_offsite": "0",
      "avoided_emissions_onsite_1": "0",
      "percent_of_electricity_that": "0",
      "percent_of_recs_retained": "Not Available",
      "percent_of_total_electricity": "Not Available",
      "leed_us_project_id": "Not Available",
      "default_values": "FALSE",
      "temporary_values": "false",
      "estimated_values_energy": "No",
      "estimated_values_water": "No",
      "alert_energy_meter_has_less": "Ok",
      "alert_energy_meter_has_gaps": "Ok",
      "alert_energy_meter_has": "Ok",
      "alert_energy_no_meters": "Ok",
      "alert_energy_meter_has_single": "Ok",
      "alert_property_has_no_uses": "Ok",
      "alert_water_meter_has_less": "Ok",
      "alert_data_center_issue_with": "Ok",
      "alert_gross_floor_area_is": "Ok",
      "estimated_data_flag": "No",
      "estimated_data_flag_natural": "No",
      "estimated_data_flag_district": "Not Available",
      "estimated_data_flag_1": "Not Available",
      "estimated_data_flag_fuel": "Not Available",
      "estimated_data_flag_fuel_1": "Not Available",
      "estimated_data_flag_fuel_2": "No",
      "estimated_data_flag_fuel_3": "Not Available",
      "estimated_data_flag_diesel": "Not Available",
      "estimated_data_flag_2": "Not Available",
      "data_center_ups_output_meter": "Not Available",
      "data_center_pdu_input_meter": "Not Available",
      "data_center_pdu_output_meter": "Not Available",
      "data_center_it_equipment": "Not Available",
      "data_center_it_site_energy": "Not Available",
      "data_center_it_source_energy": "Not Available",
      "data_center_pue": "Not Available",
      "data_center_national_median": "Not Available",
      "data_center_gross_floor_area": "Not Available",
      "data_center_ups_system": "Not Available",
      "data_center_it_energy": "Not Available",
      "data_center_energy_estimates": "Not Available",
      "data_center_cooling_equipment": "Not Available",
      "adult_education_gross_floor": "Not Available",
      "ambulatory_surgical_center": "Not Available",
      "automobile_dealership_gross": "Not Available",
      "bank_branch_gross_floor_area": "Not Available",
      "barracks_gross_floor_area": "Not Available",
      "college_university_gross": "Not Available",
      "convention_center_gross_floor": "Not Available",
      "courthouse_gross_floor_area": "Not Available",
      "distribution_center_gross": "Not Available",
      "enclosed_mall_gross_floor": "Not Available",
      "energy_power_station_gross": "Not Available",
      "financial_office_gross_floor": "Not Available",
      "financial_office_number_of": "Not Available",
      "financial_office_weekly": "Not Available",
      "financial_office_number_of_1": "Not Available",
      "fitness_center_health_club": "Not Available",
      "food_sales_gross_floor_area": "Not Available",
      "food_service_gross_floor": "Not Available",
      "hospital_general_medical": "Not Available",
      "hospital_general_medical_1": "Not Available",
      "hospital_general_medical_2": "Not Available",
      "hospital_general_medical_3": "Not Available",
      "hospital_general_medical_4": "Not Available",
      "hospital_general_medical_5": "Not Available",
      "hospital_general_medical_6": "Not Available",
      "hospital_general_medical_7": "Not Available",
      "hospital_general_medical_8": "Not Available",
      "hospital_general_medical_9": "Not Available",
      "hospital_general_medical_10": "Not Available",
      "medical_office_gross_floor": "Not Available",
      "medical_office_number_of": "Not Available",
      "medical_office_number_of_1": "Not Available",
      "medical_office_number_of_2": "Not Available",
      "medical_office_percent_that": "Not Available",
      "medical_office_percent_that_1": "Not Available",
      "medical_office_weekly": "Not Available",
      "outpatient_rehabilitation": "Not Available",
      "urgent_care_clinic_other": "Not Available",
      "hotel_gross_floor_area_ft": "Not Available",
      "hotel_gym_fitness_center": "Not Available",
      "k_12_school_gross_floor_area": "135600",
      "pre_school_daycare_gross": "Not Available",
      "laboratory_gross_floor_area": "Not Available",
      "mailing_center_post_office": "Not Available",
      "movie_theater_gross_floor": "Not Available",
      "manufacturing_industrial": "Not Available",
      "multifamily_housing_government": "Not Available",
      "multifamily_housing_gross": "Not Available",
      "multifamily_housing_number": "Not Available",
      "multifamily_housing_number_1": "Not Available",
      "multifamily_housing_number_2": "Not Available",
      "multifamily_housing_number_3": "Not Available",
      "multifamily_housing_number_4": "Not Available",
      "multifamily_housing_percent": "Not Available",
      "multifamily_housing_percent_1": "Not Available",
      "multifamily_housing_total": "Not Available",
      "multifamily_housing_total_1": "Not Available",
      "multifamily_housing_number_5": "Not Available",
      "multifamily_housing_number_6": "Not Available",
      "multifamily_housing_number_7": "Not Available",
      "multifamily_housing_resident": "Not Available",
      "residence_hall_dormitory": "Not Available",
      "refrigerated_warehouse_gross": "Not Available",
      "non_refrigerated_warehouse": "Not Available",
      "office_gross_floor_area_ft": "Not Available",
      "office_number_of_computers": "Not Available",
      "office_number_of_workers": "Not Available",
      "office_percent_that_can_be": "Not Available",
      "office_percent_that_can_be_1": "Not Available",
      "office_weekly_operating_hours": "Not Available",
      "office_worker_density_number": "Not Available",
      "other_gross_floor_area_ft": "Not Available",
      "museum_gross_floor_area_ft": "Not Available",
      "performing_arts_gross_floor": "Not Available",
      "parking_gross_floor_area": "Not Available",
      "parking_open_parking_lot": "Not Available",
      "parking_completely_enclosed": "Not Available",
      "parking_partially_enclosed": "Not Available",
      "restaurant_gross_floor_area": "Not Available",
      "restaurant_weekly_operating": "Not Available",
      "restaurant_worker_density": "Not Available",
      "retail_store_gross_floor": "Not Available",
      "retail_store_number_of_walk": "Not Available",
      "retail_store_number_of_open": "Not Available",
      "self_storage_facility_gross": "Not Available",
      "senior_living_community_gross": "Not Available",
      "senior_living_community_living": "Not Available",
      "social_meeting_hall_gross": "Not Available",
      "supermarket_grocery_gross": "Not Available",
      "supermarket_grocery_number": "Not Available",
      "supermarket_grocery_number_1": "Not Available",
      "wholesale_club_supercenter": "Not Available",
      "wholesale_club_supercenter_1": "Not Available",
      "wastewater_treatment_plant": "Not Available",
      "worship_facility_gross_floor": "Not Available",
      "strip_mall_gross_floor_area": "Not Available",
      "property_gfa_self_reported": "135600",
      "property_gfa_calculated": "135600",
      "property_gfa_calculated_1": "135600",
      "property_gfa_calculated_2": "Not Available",
      "property_notes": "Not Available",
      "water_use_all_water_sources": "826.6",
      "indoor_water_use_all_water": "826.6",
      "outdoor_water_use_all_water": "Not Available",
      "municipally_supplied_potable": "Not Available",
      "municipally_supplied_potable_1": "826.6",
      "municipally_supplied_potable_2": "826.6",
      "municipally_supplied_potable_3": "Not Available",
      "third_party_certification": "Not Available",
      "third_party_certification_1": "Not Available",
      "third_party_certification_2": "Not Available",
      "last_modified_date_property": "2023-04-24T00:00:00.000",
      "last_modified_date_electric": "2023-04-19T00:00:00.000",
      "last_modified_date_gas_meters": "2023-04-20T00:00:00.000",
      "last_modified_date_non": "2023-04-20T00:00:00.000",
      "last_modified_date_water": "2023-04-24T00:00:00.000",
      "last_modified_date_property_1": "2020-08-17T00:00:00.000",
      "last_modified_date_property_2": "2020-08-17T00:00:00.000",
      "number_of_active_energy_meters": "3",
      "number_of_active_energy_meters_1": "3",
      "number_of_active_energy_meters_2": "0",
      "number_of_active_it_meters": "0",
      "report_generation_date": "2023-05-01T16:31:00.000",
      "report_submission_date": "2023-05-01T16:37:00.000",
      "borough": "BROOKLYN",
      "latitude": "40.672015",
      "longitude": "-73.983947",
      "community_board": "306",
      "council_district": "39",
      "ct2020": "135",
      "nta2020": "BK0602"
    }
  ]
}